odoo/addons/crm_claim_sale/README.rst
odoo/addons/crm_claim_sale/__init__.py
odoo/addons/crm_claim_sale/__manifest__.py
odoo/addons/crm_claim_sale/i18n/es.po
odoo/addons/crm_claim_sale/models/__init__.py
odoo/addons/crm_claim_sale/models/crm_claim.py
odoo/addons/crm_claim_sale/models/sale_order.py
odoo/addons/crm_claim_sale/models/sale_order_type.py
odoo/addons/crm_claim_sale/static/description/icon.png
odoo/addons/crm_claim_sale/views/crm_claim_views.xml
odoo/addons/crm_claim_sale/views/sale_order_type_view.xml
odoo/addons/crm_claim_sale/views/sale_order_views.xml
odoo_addon_crm_claim_sale-15.0.1.0.1.dist-info/METADATA
odoo_addon_crm_claim_sale-15.0.1.0.1.dist-info/WHEEL
odoo_addon_crm_claim_sale-15.0.1.0.1.dist-info/top_level.txt
odoo_addon_crm_claim_sale-15.0.1.0.1.dist-info/RECORD
